{
  "$schema": "https://gist.githubusercontent.com/stackra-user/073a1ab687cd93ede7ae927b96a025ea/raw/catalog.v1.json",
  "name": "stackra/foundation",
  "tier": "foundation",
  "surfaces": ["core"],
  "kind": "framework-plumbing",
  "purpose": "Shared kernel for every Stackra package: module service-provider base, cross-cutting contracts, correlation-id middleware, guard clauses, and testable clock.",
  "capabilities": [
    "Declarative module service-provider base class",
    "Cross-cutting contracts (HasErrorCode, HasContext, HasUserMessage, Correlatable, Clock)",
    "AssignCorrelationId middleware for every request",
    "Guard-clause helpers (Assert::notNull, notEmpty, inRange)",
    "Testable Clock abstraction with SystemClock default",
    "AppEnvironment enum for Laravel environments"
  ],
  "when_to_use": "Every Stackra backend package depends on it — the shared kernel every other package composes from.",
  "when_not_to_use": "For persistence, migrations, or repositories, reach for stackra/database or stackra/crud instead.",
  "peer_deps": [
    "stackra/enum",
    "stackra/service-provider",
    "olvlvl/composer-attribute-collector"
  ],
  "backend_pair": null,
  "size_gzip_kb": {},
  "maturity": "alpha",
  "owning_agent": "laravel-feature-builder",
  "docs": ["packages/backend/foundation/README.md"]
}
